ngs_pipeline_lib/__init__.py
ngs_pipeline_lib/api/__init__.py
ngs_pipeline_lib/api/models.py
ngs_pipeline_lib/api/security.py
ngs_pipeline_lib/base/__init__.py
ngs_pipeline_lib/base/algorithm.py
ngs_pipeline_lib/base/file.py
ngs_pipeline_lib/base/inputs.py
ngs_pipeline_lib/base/outputs.py
ngs_pipeline_lib/base/report.py
ngs_pipeline_lib/biotools/__init__.py
ngs_pipeline_lib/biotools/biotools.py
ngs_pipeline_lib/cli/__init__.py
ngs_pipeline_lib/tools/__init__.py
ngs_pipeline_lib/tools/json.py
ngs_pipeline_lib/tools/parallel.py
ngs_pipeline_lib/tools/quality_control/__init__.py
ngs_pipeline_lib/tools/quality_control/assembly.py
ngs_pipeline_lib/tools/quality_control/operators.py
ngs_pipeline_lib/tools/quality_control/quality_control.py
ngs_pipeline_lib/tools/quality_control/rules.py
ngs_pipeline_lib/tools/runextern.py
ngs_pipeline_lib/tools/s3.py
ngs_pipeline_lib/tools/stub.py
ngs_pipeline_lib/tools/tools.py
scripts/__init__.py
scripts/api/__init__.py
scripts/api/main.py
scripts/common/models.py
scripts/docker/__init__.py
scripts/docker/main.py
scripts/docker/models.py
scripts/run/__init__.py
scripts/run/main.py
scripts/tests/__init__.py
scripts/tests/e2e.py
scripts/tests/exceptions.py
scripts/tests/integration.py
scripts/tests/main.py
scripts/tests/models/__init__.py
scripts/tests/models/common.py
scripts/tests/models/e2e.py
scripts/tests/models/integration.py
scripts/tests/utils/__init__.py
scripts/tests/utils/common.py
scripts/tests/utils/e2e.py
scripts/tests/utils/integration.py
ngs_pipeline_lib-5.1.3.dist-info/entry_points.txt
ngs_pipeline_lib-5.1.3.dist-info/WHEEL
ngs_pipeline_lib-5.1.3.dist-info/METADATA
ngs_pipeline_lib-5.1.3.dist-info/RECORD
