Metadata-Version: 2.1
Name: ngs-pipeline-lib
Version: 5.1.3
Summary: Common code used by every processes in Bio Pipelines
Author: Vincent ROHOU
Author-email: vincent.rohou@ext.biomerieux.com
Requires-Python: >=3.11,<4.0
Classifier: Programming Language :: Python :: 3
Requires-Dist: boto3 (>=1.28.52,<2.0.0)
Requires-Dist: clidantic (>=0.1.0,<0.2.0)
Requires-Dist: colorama (>=0.4.6,<0.5.0)
Requires-Dist: coverage (>=7.2.7,<8.0.0)
Requires-Dist: docker (>=7.0.0,<8.0.0)
Requires-Dist: fastapi (>=0.111.0,<0.112.0)
Requires-Dist: flatdict (>=4.0.1,<5.0.0)
Requires-Dist: pgzip (>=0.3.5,<0.4.0)
Requires-Dist: pydantic[dotenv] (>=1.10.7,<2.0.0)
Requires-Dist: pyjwt (>=2.8.0,<3.0.0)
Requires-Dist: pytest-mock (>=3.10.0,<4.0.0)
Requires-Dist: structlog (>=24.1.0,<25.0.0)
